LICENSE.txt
MANIFEST.in
README.rst
setup.cfg
setup.py
django_ocr_server/__init__.py
django_ocr_server/admin.py
django_ocr_server/apiviews.py
django_ocr_server/apps.py
django_ocr_server/converters.py
django_ocr_server/exceptions.py
django_ocr_server/forms.py
django_ocr_server/models.py
django_ocr_server/serializers.py
django_ocr_server/settings.py
django_ocr_server/tests.py
django_ocr_server/urls.py
django_ocr_server/utils.py
django_ocr_server/views.py
django_ocr_server/widgets.py
django_ocr_server.egg-info/PKG-INFO
django_ocr_server.egg-info/SOURCES.txt
django_ocr_server.egg-info/dependency_links.txt
django_ocr_server.egg-info/entry_points.txt
django_ocr_server.egg-info/requires.txt
django_ocr_server.egg-info/top_level.txt
django_ocr_server/management/__init__.py
django_ocr_server/management/commands/__init__.py
django_ocr_server/management/commands/clean.py
django_ocr_server/management/commands/create_user.py
django_ocr_server/management/commands/db_ping.py
django_ocr_server/management/commands/ttl.py
django_ocr_server/migrations/0001_initial.py
django_ocr_server/migrations/__init__.py
django_ocr_server/static/django_ocr_server/django-ocr-server.png
django_ocr_server/static/django_ocr_server/django-ocr-server.svg
django_ocr_server/static/django_ocr_server/style.css
django_ocr_server/templates/admin/django_ocr_server/ocredfile/submit_line.html
django_ocr_server/templates/django_ocr_server/base.html
django_ocr_server/templates/django_ocr_server/main_page.html
django_ocr_server/templates/django_ocr_server/forms/widgets/file_link.html
django_ocr_server/templates/django_ocr_server/forms/widgets/pdf_info.html
django_ocr_server/templates/django_ocr_server/forms/widgets/pdf_link.html
django_ocr_server/tests/deming.pdf
django_ocr_server/tests/not_image.txt
django_ocr_server/tests/shmakovpn.jpg
django_ocr_server/tests/shmakovpn.pdf
django_ocr_server/tests/test_eng.pdf
django_ocr_server/tests/test_eng.png
django_ocr_server/tests/test_eng_notext.pdf
django_ocr_server/tests/test_rus.png
django_ocr_server/tests/the_pdf_withtext.pdf