Metadata-Version: 1.1
Name: django-ocr-server
Version: 1.9
Summary: UNKNOWN
Home-page: https://github.com/shmakovpn/django_ocr_server
Author: shmakovpn
Author-email: shmakovpn@yandex.ru
License: UNKNOWN
Download-URL: https://github.com/shmakovpn/django_ocr_server/archive/1.9.zip
Platform: UNKNOWN
